pyxq/__init__.py
pyxq/ba.py
pyxq/cb.py
pyxq/cn.py
pyxq/itf.py
pyxq/actor/__init__.py
pyxq/app/__init__.py
pyxq/msg/__init__.py
pyxq/msg/fa.py
pyxq/msg/md.py
pyxq/msg/pa.py
pyxq/msg/td.py
pyxq/service/__init__.py
pyxq/service/account.py
pyxq-0.1.5.post0.dist-info/AUTHORS.rst
pyxq-0.1.5.post0.dist-info/LICENSE
pyxq-0.1.5.post0.dist-info/METADATA
pyxq-0.1.5.post0.dist-info/WHEEL
pyxq-0.1.5.post0.dist-info/top_level.txt
pyxq-0.1.5.post0.dist-info/RECORD
