Metadata-Version: 2.1
Name: pyxq
Version: 0.1.5.post0
Summary: python quant is so easy.
Home-page: https://github.com/goodchinas/pyxq
Author: tim
Author-email: goodchinas@qq.com
License: MIT license
Keywords: pyxq
Platform: UNKNOWN
Classifier: Development Status :: 2 - Pre-Alpha
Classifier: Intended Audience :: Developers
Classifier: License :: OSI Approved :: MIT License
Classifier: Natural Language :: English
Classifier: Programming Language :: Python :: 3.7
